{"emb_size_month":400,
 "emb_size_hour":400,
 "emb_size_lat_lon":400,
 "emb_size_init_time":400,
 "emb_size_lead_time":400,
 "layer1":1000,
 "layer2":800,
 "layer3":600,
 "layer4":400,
 "layer5":300,
 "layer6":200,
 "layer7":100,
 "layer8":50,
 "layer9":20,
 "layer10":1,
 "exp_name": "mv_mv",
 "num_epochs":100,
 "shuffle_buffer_size" : 10,
 "batch_size":8192,
 "validate_every_x_batches":10,
 "use_comet_experiments":true,
 "comet_api_key" : "YNVsumiYWc7SZi21EhZzy7e6y",
 "comet_project_name" : "dslab2019-meteoswisscloud",
 "comet_workspace" : "ferraric"
}
